ssa_translation_lowmem.cp38-win_amd64.pyd
rsnapsim_ssa_cpp-0.0.23.dist-info/METADATA
rsnapsim_ssa_cpp-0.0.23.dist-info/WHEEL
rsnapsim_ssa_cpp-0.0.23.dist-info/top_level.txt
rsnapsim_ssa_cpp-0.0.23.dist-info/RECORD
