Metadata-Version: 2.1
Name: rsnapsim-ssa-cpp
Version: 0.0.23
Summary: mRNA translation Stochastic Simulation Algorithms (SSA) for the rSNAPsim module.
Home-page: https://github.com/MunskyGroup/rSNAPsim
Author: William Raymond
Author-email: wsraymon@rams.colostate.edu
License: UNKNOWN
Platform: UNKNOWN
Requires-Dist: numpy
Requires-Dist: Cython (>=0.26.0)
